{
  "db_name": "SQLite",
  "query": "SELECT last_grow, prestige_level FROM dicks WHERE user_id = ? AND guild_id = ?",
  "describe": {
    "columns": [
      {
        "name": "last_grow",
        "ordinal": 0,
        "type_info": "Text"
      },
      {
        "name": "prestige_level",
        "ordinal": 1,
        "type_info": "Integer"
      }
    ],
    "parameters": {
      "Right": 2
    },
    "nullable": [
      false,
      false
    ]
  },
  "hash": "a40d55a7254e4dfa6a940c46d95b8d5c62819fbfa39f1b509edcd9f44937e8f4"
}
